cktap/__init__.py
cktap/_ecdsa.py
cktap/base58.py
cktap/bech32.py
cktap/bip32.py
cktap/cli.py
cktap/compat.py
cktap/constants.py
cktap/descriptors.py
cktap/exceptions.py
cktap/proto.py
cktap/ripemd.py
cktap/sweep.py
cktap/test.py
cktap/transport.py
cktap/uploads.py
cktap/utils.py
cktap/verify_link.py
cktap/version.py
cktap/wrap_coincurve.py
cktap/wrap_ecdsa.py
cktap/wrap_pysecp.py
cktap/wrap_wally.py
coinkite_tap_protocol-1.2.2.dist-info/COPYING-CC
coinkite_tap_protocol-1.2.2.dist-info/LICENSE
coinkite_tap_protocol-1.2.2.dist-info/METADATA
coinkite_tap_protocol-1.2.2.dist-info/WHEEL
coinkite_tap_protocol-1.2.2.dist-info/entry_points.txt
coinkite_tap_protocol-1.2.2.dist-info/top_level.txt
coinkite_tap_protocol-1.2.2.dist-info/RECORD
