Metadata-Version: 2.1
Name: coinkite-tap-protocol
Version: 1.2.2
Summary: Communicate with your TAPSIGNER or SATSCARD using Python
Home-page: https://github.com/coinkite/coinkite-tap-proto
Author: Coinkite Inc.
Author-email: support@coinkite.com
License: UNKNOWN
Platform: UNKNOWN
Classifier: Operating System :: POSIX :: Linux
Classifier: Operating System :: Microsoft :: Windows
Classifier: Operating System :: MacOS :: MacOS X
Requires-Python: >3.6.0
License-File: LICENSE
License-File: COPYING-CC
Requires-Dist: cbor2 (>=5.4.1)
Provides-Extra: cli
Requires-Dist: pyscard (>=2.0.2) ; extra == 'cli'
Requires-Dist: click (>=8.0.3) ; extra == 'cli'
Requires-Dist: pyqrcode (>=1.2.1) ; extra == 'cli'
Requires-Dist: pypng (>=0.0.21) ; extra == 'cli'
Requires-Dist: requests[socks] (>=2.26.0) ; extra == 'cli'
Provides-Extra: test
Requires-Dist: pyscard (>=2.0.2) ; extra == 'test'
Requires-Dist: pytest ; extra == 'test'
Requires-Dist: requests[socks] (>=2.26.0) ; extra == 'test'
Provides-Extra: test_plus
Requires-Dist: pyscard (>=2.0.2) ; extra == 'test_plus'
Requires-Dist: pytest ; extra == 'test_plus'
Requires-Dist: requests[socks] (>=2.26.0) ; extra == 'test_plus'
Requires-Dist: coincurve (>=15.0.1) ; extra == 'test_plus'
Requires-Dist: wallycore (>=0.8.2) ; extra == 'test_plus'
